cmdbox/__init__.py
cmdbox/__main__.py
cmdbox/autoload.py
cmdbox/logconf_cmdbox.yml
cmdbox/version.py
cmdbox/app/__init__.py
cmdbox/app/a2a.py
cmdbox/app/app.py
cmdbox/app/client.py
cmdbox/app/common.py
cmdbox/app/edge.py
cmdbox/app/edge_tool.py
cmdbox/app/feature.py
cmdbox/app/filer.py
cmdbox/app/mcp.py
cmdbox/app/options.py
cmdbox/app/server.py
cmdbox/app/web.py
cmdbox/app/auth/__init__.py
cmdbox/app/auth/azure_signin.py
cmdbox/app/auth/azure_signin_saml.py
cmdbox/app/auth/github_signin.py
cmdbox/app/auth/google_signin.py
cmdbox/app/auth/signin.py
cmdbox/app/auth/signin_saml.py
cmdbox/app/commons/convert.py
cmdbox/app/commons/loghandler.py
cmdbox/app/commons/module.py
cmdbox/app/commons/redis_client.py
cmdbox/app/features/cli/_cmdbox_vision_install.py
cmdbox/app/features/cli/_cmdbox_vision_predict.py
cmdbox/app/features/cli/_cmdbox_vision_start.py
cmdbox/app/features/cli/audit_base.py
cmdbox/app/features/cli/cmdbox_a2asv_start.py
cmdbox/app/features/cli/cmdbox_a2asv_stop.py
cmdbox/app/features/cli/cmdbox_agent_agent_del.py
cmdbox/app/features/cli/cmdbox_agent_agent_list.py
cmdbox/app/features/cli/cmdbox_agent_agent_load.py
cmdbox/app/features/cli/cmdbox_agent_agent_save.py
cmdbox/app/features/cli/cmdbox_agent_chat.py
cmdbox/app/features/cli/cmdbox_agent_llm_del.py
cmdbox/app/features/cli/cmdbox_agent_llm_list.py
cmdbox/app/features/cli/cmdbox_agent_llm_load.py
cmdbox/app/features/cli/cmdbox_agent_llm_save.py
cmdbox/app/features/cli/cmdbox_agent_mcp_client.py
cmdbox/app/features/cli/cmdbox_agent_mcp_proxy.py
cmdbox/app/features/cli/cmdbox_agent_mcpsv_del.py
cmdbox/app/features/cli/cmdbox_agent_mcpsv_list.py
cmdbox/app/features/cli/cmdbox_agent_mcpsv_load.py
cmdbox/app/features/cli/cmdbox_agent_mcpsv_save.py
cmdbox/app/features/cli/cmdbox_agent_runner_del.py
cmdbox/app/features/cli/cmdbox_agent_runner_list.py
cmdbox/app/features/cli/cmdbox_agent_runner_load.py
cmdbox/app/features/cli/cmdbox_agent_runner_save.py
cmdbox/app/features/cli/cmdbox_agent_session_del.py
cmdbox-0.7.2.3.dist-info/licenses/LICENSE
cmdbox-0.7.2.3.dist-info/METADATA
cmdbox-0.7.2.3.dist-info/WHEEL
cmdbox-0.7.2.3.dist-info/entry_points.txt
cmdbox-0.7.2.3.dist-info/top_level.txt
cmdbox-0.7.2.3.dist-info/RECORD
