Metadata-Version: 2.4
Name: cmdbox
Version: 0.7.2.3
Summary: cmdbox: It is a command line application with a plugin mechanism.
Author-email: hamacom2004jp <hamacom2004jp@gmail.com>
License: MIT
Project-URL: Homepage, https://github.com/hamacom2004jp/cmdbox
Project-URL: Documentation, https://hamacom2004jp.github.io/cmdbox/index.html
Project-URL: Repository, https://github.com/hamacom2004jp/cmdbox
Keywords: audit,cli,excel,fastapi,mcp,redis,restapi,web
Classifier: Development Status :: 4 - Beta
Classifier: Intended Audience :: Developers
Classifier: Intended Audience :: Information Technology
Classifier: Intended Audience :: System Administrators
Classifier: License :: OSI Approved :: MIT License
Classifier: Natural Language :: Japanese
Classifier: Programming Language :: Python
Classifier: Topic :: Utilities
Requires-Python: >=3.8
License-File: LICENSE
Requires-Dist: argcomplete
Requires-Dist: aiosqlite
Requires-Dist: async-timeout
Requires-Dist: cffi
Requires-Dist: cryptography
Requires-Dist: fastapi
Requires-Dist: debugpy
Requires-Dist: gevent
Requires-Dist: gunicorn
Requires-Dist: itsdangerous
Requires-Dist: numpy
Requires-Dist: openpyxl
Requires-Dist: Pillow
Requires-Dist: plyer
Requires-Dist: psycopg[binary]
Requires-Dist: pyjwt
Requires-Dist: pystray
Requires-Dist: python-multipart
Requires-Dist: pycryptodome
Requires-Dist: pyyaml
Requires-Dist: questionary
Requires-Dist: redis
Requires-Dist: requests
Requires-Dist: rich
Requires-Dist: six
Requires-Dist: tabulate
Requires-Dist: uvicorn
Requires-Dist: wsproto
Requires-Dist: wheel
Provides-Extra: agent
Requires-Dist: pydantic<3.0.0,>=2.0.0; extra == "agent"
Requires-Dist: fastmcp>=2.14.0; extra == "agent"
Requires-Dist: mcp<2.0.0,>=1.10.0; extra == "agent"
Requires-Dist: google-adk>=1.21.0; extra == "agent"
Requires-Dist: a2a-sdk<0.4.0,>=0.3.4; extra == "agent"
Requires-Dist: litellm; extra == "agent"
Provides-Extra: saml
Requires-Dist: python3-saml; extra == "saml"
Requires-Dist: xmlsec==1.3.13; extra == "saml"
Dynamic: license-file
